{
  "camera": {
    "fov": 45,
    "lookAt": { "x": 0, "y": 1, "z": 0 },
    "position": { "x": -10, "y": 3, "z": 10 },
    "up": { "x": 0, "y": 1, "z": 0 }
  },
  "config": {
    "height": 600,
    "output_file": "output.png",
    "width": 1000
  },
  "scene": {
    "ambient_light": { "r": 0.4, "g": 0.4, "b": 0.4 },
    "lights": [
      {
        "type": "point",
        "position": { "x": -5, "y": 8, "z": 5 },
        "intensity": { "r": 1, "g": 1, "b": 1 }
      }
    ],
    "objects": [
      {
        "type": "plane",
        "normal": { "x": 0, "y": 1, "z": 0 },
        "distance": 0,
        "material": {
          "color": { "r": 0.6, "g": 0.6, "b": 0.6 },
          "diffuse": 0.8,
          "specular": 0.3,
          "shininess": 32,
          "reflectivity": 0.4
        }
      },
      {
        "type": "sphere",
        "center": { "x": -3, "y": 1, "z": 0 },
        "radius": 1,
        "material": {
          "color": { "r": 0.5, "g": 0, "b": 0.7 },
          "diffuse": 0.7,
          "specular": 0.5,
          "shininess": 64,
          "reflectivity": 0.4
        }
      },
      {
        "type": "sphere",
        "center": { "x": 0, "y": 1, "z": 0 },
        "radius": 1,
        "material": {
          "color": { "r": 1, "g": 1, "b": 1 },
          "diffuse": 0.7,
          "specular": 0.7,
          "shininess": 128,
          "reflectivity": 0.6
        }
      },
      {
        "type": "sphere",
        "center": { "x": 3, "y": 1, "z": 0 },
        "radius": 1,
        "material": {
          "color": { "r": 1, "g": 0, "b": 0 },
          "diffuse": 0.7,
          "specular": 0.6,
          "shininess": 96,
          "reflectivity": 0.5
        }
      }
    ]
  }
}
